pymdma/__init__.py
pymdma/__main__.py
pymdma/cli.py
pymdma/common/__init__.py
pymdma/common/compute.py
pymdma/common/definitions.py
pymdma/common/output.py
pymdma/common/selection.py
pymdma/common/settings.py
pymdma/common/viz.py
pymdma/config.py
pymdma/constants.py
pymdma/general/__init__.py
pymdma/general/functional/__init__.py
pymdma/general/functional/distance.py
pymdma/general/functional/knn.py
pymdma/general/functional/ratio.py
pymdma/general/measures/__init__.py
pymdma/general/measures/external/__init__.py
pymdma/general/measures/external/piq.py
pymdma/general/measures/prd.py
pymdma/general/measures/prdc.py
pymdma/general/models/__init__.py
pymdma/general/models/kernels.py
pymdma/general/utils/__init__.py
pymdma/general/utils/util.py
pymdma/image/__init__.py
pymdma/image/data/__init__.py
pymdma/image/data/parsers.py
pymdma/image/data/simple_dataset.py
pymdma/image/input_layer.py
pymdma/image/measures/__init__.py
pymdma/image/measures/input_val/__init__.py
pymdma/image/measures/input_val/annotation/__init__.py
pymdma/image/measures/input_val/annotation/coco.py
pymdma/image/measures/input_val/data/__init__.py
pymdma/image/measures/input_val/data/dom.py
pymdma/image/measures/input_val/data/no_reference.py
pymdma/image/measures/input_val/data/psnr.py
pymdma/image/measures/input_val/data/ssim.py
pymdma/image/measures/synthesis_val/__init__.py
pymdma/image/measures/synthesis_val/feature/__init__.py
pymdma/image/measures/synthesis_val/feature/_shared.py
pymdma/image/measures/synthesis_val/feature/giqa.py
pymdma/image/models/__init__.py
pymdma/image/models/extractor.py
pymdma/image/models/features.py
pymdma/image/models/imagenet.py
pymdma/image/utils/__init__.py
pymdma/image/utils/processing.py
pymdma/tabular/__init__.py
pymdma/tabular/data/__init__.py
pymdma/tabular/data/harmonize.py
pymdma/tabular/data/load.py
pymdma/tabular/data/utils.py
pymdma/tabular/embeddings/__init__.py
pymdma/tabular/embeddings/embed.py
pymdma/tabular/embeddings/impute.py
pymdma-0.2.2.dist-info/AUTHORS.md
pymdma-0.2.2.dist-info/LICENSE
pymdma-0.2.2.dist-info/METADATA
pymdma-0.2.2.dist-info/WHEEL
pymdma-0.2.2.dist-info/entry_points.txt
pymdma-0.2.2.dist-info/RECORD
