Metadata-Version: 2.1
Name: pymdma
Version: 0.2.2
Summary: Multimodal Data Metrics for Auditing real and synthetic data
Home-page: https://github.com/fraunhoferportugal/pymdma
License: LGPL-3.0-or-later
Author: Fraunhofer AICOS
Author-email: no-reply@aicos.fraunhofer.pt
Maintainer: Ivo Façoco
Maintainer-email: ivo.facoco@aicos.fraunhofer.pt
Requires-Python: >=3.9,<4.0
Classifier: Development Status :: 5 - Production/Stable
Classifier: License :: OSI Approved :: GNU Lesser General Public License v3 (LGPLv3)
Classifier: License :: OSI Approved :: GNU Lesser General Public License v3 or later (LGPLv3+)
Classifier: Operating System :: OS Independent
Classifier: Programming Language :: Python :: 3
Classifier: Programming Language :: Python :: 3.9
Classifier: Programming Language :: Python :: 3.10
Classifier: Programming Language :: Python :: 3.11
Classifier: Programming Language :: Python :: 3.12
Classifier: Programming Language :: Python :: 3.13
Classifier: Topic :: Scientific/Engineering :: Artificial Intelligence
Classifier: Topic :: Scientific/Engineering :: Information Analysis
Provides-Extra: all
Provides-Extra: image
Provides-Extra: tabular
Provides-Extra: time-series
Requires-Dist: fastdtw (>=0.3.4,<0.4.0) ; extra == "time-series" or extra == "all"
Requires-Dist: gudhi (>=3.9.0,<=4.0.0) ; extra == "tabular" or extra == "all"
Requires-Dist: loguru (>=0.7.2,<0.8.0)
Requires-Dist: matplotlib (>=3.4.3,<4.0.0)
Requires-Dist: numba (>=0.60.0,<0.80.0) ; extra == "tabular" or extra == "all"
Requires-Dist: numpy (>=1.22.0,<2.5.0)
Requires-Dist: opencv-python (>=4.10.0.84,<4.15.0.0) ; extra == "image" or extra == "all"
Requires-Dist: pandas (>=2.0.0,<3.0.0) ; extra == "tabular" or extra == "all"
Requires-Dist: piq (>=0.8.0,<1.0.0)
Requires-Dist: pot (>=0.9.4,<0.10.0)
Requires-Dist: pycanon (==1.0.1.post2) ; extra == "tabular" or extra == "all"
Requires-Dist: pycocotools (>=2.0.8) ; extra == "image" or extra == "all"
Requires-Dist: pydantic (>=2.8.2,<3.0.0)
Requires-Dist: python-dotenv (>=1.0.0,<2.0.0)
Requires-Dist: scikit-learn (>1.4.0)
Requires-Dist: scipy (>=1.6.0,<2.0.0) ; extra == "tabular" or extra == "all"
Requires-Dist: spacy (>=3.7.4,<4.0.0) ; extra == "tabular" or extra == "all"
Requires-Dist: statsmodels (>=0.14.4,<0.15.0) ; extra == "tabular" or extra == "time-series" or extra == "all"
Requires-Dist: torch (>=2.1.0,<2.9.0)
Requires-Dist: torchvision (>=0.15.2,<0.26.0) ; extra == "image" or extra == "all"
Requires-Dist: transformers (>=4.43.2,<5.0.0) ; extra == "tabular" or extra == "all"
Requires-Dist: tsfel (>0.1.7) ; extra == "time-series" or extra == "all"
Requires-Dist: umap-learn (>=0.5.5,<0.6.0) ; extra == "tabular" or extra == "all"
Requires-Dist: wfdb (>=4.1.2,<5.0.0) ; extra == "time-series" or extra == "all"
Requires-Dist: word2number (>=1.1.0,<1.5.0) ; extra == "tabular" or extra == "all"
Project-URL: Documentation, https://pymdma.readthedocs.io/en/latest/
Project-URL: Repository, https://github.com/fraunhoferportugal/pymdma
